CHANGELOG.rst
CONTRIBUTORS.rst
LICENSE.txt
MANIFEST.in
README.rst
requirements.txt
setup.py
docs/Makefile
docs/__init__.py
docs/conf.py
docs/index.rst
docs/api/aleph_link_export.rst
docs/api/link_export.rst
docs/api/request_database.rst
docs/api/settings.rst
docs/api/shelvedb.rst
docs/api/structures/requests.rst
docs/api/structures/responses.rst
docs/api/structures/structures.rst
docs/notes/protocol_notes.rst
src/edeposit/__init__.py
src/edeposit.amqp.aleph_link_export.egg-info/PKG-INFO
src/edeposit.amqp.aleph_link_export.egg-info/SOURCES.txt
src/edeposit.amqp.aleph_link_export.egg-info/dependency_links.txt
src/edeposit.amqp.aleph_link_export.egg-info/namespace_packages.txt
src/edeposit.amqp.aleph_link_export.egg-info/not-zip-safe
src/edeposit.amqp.aleph_link_export.egg-info/requires.txt
src/edeposit.amqp.aleph_link_export.egg-info/top_level.txt
src/edeposit/amqp/__init__.py
src/edeposit/amqp/aleph_link_export/__init__.py
src/edeposit/amqp/aleph_link_export/link_export.py
src/edeposit/amqp/aleph_link_export/request_database.py
src/edeposit/amqp/aleph_link_export/settings.py
src/edeposit/amqp/aleph_link_export/shelvedb.py
src/edeposit/amqp/aleph_link_export/structures/__init__.py
src/edeposit/amqp/aleph_link_export/structures/requests.py
src/edeposit/amqp/aleph_link_export/structures/responses.py
tests/test_RequestDatabase.py
tests/test_amqp_chain.py
tests/structures/__init__.py
tests/structures/test_requests.py
tests/structures/test_responses.py