Metadata-Version: 1.1
Name: edeposit.amqp.aleph-link-export
Version: 1.2.0
Summary: Subsystem for updating Edeposit's links in Aleph.
Home-page: https://github.com/edeposit/edeposit.amqp.aleph_link_export/
Author: Edeposit team
Author-email: edeposit@email.cz
License: MIT
Platform: UNKNOWN
Classifier: Development Status :: 3 - Alpha
Classifier: Intended Audience :: Developers
Classifier: Programming Language :: Python :: 2
Classifier: Programming Language :: Python :: 2.7
Classifier: License :: OSI Approved :: MIT License
